README.rst
setup.py
metriquec/__init__.py
metriquec/argparsers.py
metriquec.egg-info/PKG-INFO
metriquec.egg-info/SOURCES.txt
metriquec.egg-info/dependency_links.txt
metriquec.egg-info/requires.txt
metriquec.egg-info/top_level.txt
metriquec/cubes/__init__.py
metriquec/cubes/csvdata/__init__.py
metriquec/cubes/csvdata/rows.py
metriquec/cubes/gitdata/__init__.py
metriquec/cubes/gitdata/repo.py
metriquec/cubes/jknsapi/__init__.py
metriquec/cubes/jknsapi/build.py
metriquec/cubes/jsondata/__init__.py
metriquec/cubes/jsondata/objs.py
metriquec/cubes/sqldata/__init__.py
metriquec/cubes/sqldata/generic.py
metriquec/cubes/sqldata/teiid.py
metriquec/sql/__init__.py
metriquec/sql/basesql.py
metriquec/sql/teiid.py