Metadata-Version: 1.1
Name: metriquec
Version: 0.2.2-7a
Summary: Metrique - Cubes
Home-page: https://github.com/drpoovilleorg/metrique
Author: Chris Ward
Author-email: cward@redhat.com
License: GPLv3
Download-URL: https://github.com/drpoovilleorg/metrique/archive/master.zip
Platform: UNKNOWN
Requires: metrique (>=0.2.2)
Requires: celery (>=3.0)
Requires: gittle (>=0.2.1)
Requires: psycopg2 (>=2.5.1)
Provides: metriquec
